README.md
setup.py
vPdfAntiAntiPlagio/__init__.py
vPdfAntiAntiPlagio/main.py
vPdfAntiAntiPlagio/wsgi.py
vPdfAntiAntiPlagio.egg-info/PKG-INFO
vPdfAntiAntiPlagio.egg-info/SOURCES.txt
vPdfAntiAntiPlagio.egg-info/dependency_links.txt
vPdfAntiAntiPlagio.egg-info/entry_points.txt
vPdfAntiAntiPlagio.egg-info/requires.txt
vPdfAntiAntiPlagio.egg-info/top_level.txt
vPdfAntiAntiPlagio/aplicacion/Aplicacion.py
vPdfAntiAntiPlagio/aplicacion/__init__.py
vPdfAntiAntiPlagio/dominio/PDFAntiantiplagio.py
vPdfAntiAntiPlagio/dominio/__init__.py
vPdfAntiAntiPlagio/infraestructura/Console.py
vPdfAntiAntiPlagio/infraestructura/Controller.py
vPdfAntiAntiPlagio/infraestructura/GUI.py
vPdfAntiAntiPlagio/infraestructura/Server.py
vPdfAntiAntiPlagio/infraestructura/__init__.py