Metadata-Version: 2.1
Name: vPdfAntiAntiPlagio
Version: 0.5.2
Summary: Aplicacion anti anti plagio
Home-page: https://github.com/ValdrST/V_pdf_Antiantiplagio
Author: Valdr Stiglitz
Author-email: valdr.stiglitz@gmail.com
License: UNKNOWN
Platform: UNKNOWN
Classifier: Programming Language :: Python :: 3
Classifier: Operating System :: OS Independent
